setup.py
pymymailru/__init__.py
pymymailru/example.py
pymymailru/pymymailru.py
pymymailru.egg-info/PKG-INFO
pymymailru.egg-info/SOURCES.txt
pymymailru.egg-info/dependency_links.txt
pymymailru.egg-info/not-zip-safe
pymymailru.egg-info/top_level.txt