Metadata-Version: 1.0
Name: pymymailru
Version: 0.5.2
Summary: Python API to MyMailRu API
Home-page: https://github.com/dbf256/py-mymailru
Author: Alexey Moskvin
Author-email: dbf256@gmail.com
License: MIT
Platform: UNKNOWN
